kba/__init__.py
kba/api_client.py
kba/configuration.py
kba/rest.py
kba/utils.py
kba/api/__init__.py
kba/api/concepts_api.py
kba/api/metadata_api.py
kba/api/statements_api.py
kba/models/__init__.py
kba/models/server_beacon_concept_category.py
kba/models/server_beacon_predicate.py
kba/models/server_clique.py
kba/models/server_cliques_query.py
kba/models/server_cliques_query_beacon_status.py
kba/models/server_cliques_query_result.py
kba/models/server_cliques_query_status.py
kba/models/server_concept.py
kba/models/server_concept_categories_by_beacon.py
kba/models/server_concept_category.py
kba/models/server_concept_detail.py
kba/models/server_concept_with_details.py
kba/models/server_concept_with_details_beacon_entry.py
kba/models/server_concepts_query.py
kba/models/server_concepts_query_beacon_status.py
kba/models/server_concepts_query_result.py
kba/models/server_concepts_query_status.py
kba/models/server_knowledge_beacon.py
kba/models/server_knowledge_map.py
kba/models/server_knowledge_map_object.py
kba/models/server_knowledge_map_predicate.py
kba/models/server_knowledge_map_statement.py
kba/models/server_knowledge_map_subject.py
kba/models/server_log_entry.py
kba/models/server_predicate.py
kba/models/server_predicates_by_beacon.py
kba/models/server_statement.py
kba/models/server_statement_annotation.py
kba/models/server_statement_citation.py
kba/models/server_statement_details.py
kba/models/server_statement_object.py
kba/models/server_statement_predicate.py
kba/models/server_statement_subject.py
kba/models/server_statements_query.py
kba/models/server_statements_query_beacon_status.py
kba/models/server_statements_query_result.py
kba/models/server_statements_query_status.py
kba-0.0.3.data/scripts/kba_cli.py
test/__init__.py
test/test_aggregator_api.py
test/test_concepts_api.py
test/test_metadata_api.py
test/test_server_beacon_concept_category.py
test/test_server_beacon_predicate.py
test/test_server_clique.py
test/test_server_cliques_query.py
kba-0.0.3.dist-info/METADATA
kba-0.0.3.dist-info/WHEEL
kba-0.0.3.dist-info/entry_points.txt
kba-0.0.3.dist-info/top_level.txt
kba-0.0.3.dist-info/RECORD
