Metadata-Version: 2.1
Name: kba
Version: 0.0.3
Summary: Translator Knowledge Beacon Aggregator API
Home-page: https://github.com/NCATS-Tangerine/beacon-aggregator-client
Author: UNKNOWN
Author-email: richard@starinformatics.com
License: UNKNOWN
Keywords: Swagger,Translator Knowledge Beacon Aggregator API
Platform: UNKNOWN
Requires-Dist: urllib3 (>=1.15)
Requires-Dist: six (>=1.10)
Requires-Dist: certifi
Requires-Dist: python-dateutil
Requires-Dist: click
Requires-Dist: progress
